octue/__init__.py
octue/cli.py
octue/cloud/__init__.py
octue/cloud/emulators/__init__.py
octue/cloud/emulators/cloud_storage.py
octue/cloud/storage/__init__.py
octue/cloud/storage/client.py
octue/cloud/storage/path.py
octue/definitions.py
octue/exceptions.py
octue/log_handlers.py
octue/mixins/__init__.py
octue/mixins/base.py
octue/mixins/cloud_pathable.py
octue/mixins/cool_nameable.py
octue/mixins/filterable.py
octue/mixins/hashable.py
octue/mixins/identifiable.py
octue/mixins/labelable.py
octue/mixins/metadata.py
octue/mixins/serialisable.py
octue/mixins/taggable.py
octue/resources/__init__.py
octue/resources/datafile.py
octue/resources/dataset.py
octue/resources/filter_containers.py
octue/resources/label.py
octue/resources/manifest.py
octue/resources/tag.py
octue/twined/__init__.py
octue/twined/app_loading.py
octue/twined/cloud/__init__.py
octue/twined/cloud/deployment/__init__.py
octue/twined/cloud/deployment/dockerfiles/Dockerfile-python310
octue/twined/cloud/deployment/dockerfiles/Dockerfile-python311
octue/twined/cloud/deployment/dockerfiles/Dockerfile-python312
octue/twined/cloud/deployment/dockerfiles/Dockerfile-python313
octue/twined/cloud/emulators/__init__.py
octue/twined/cloud/emulators/_pub_sub.py
octue/twined/cloud/emulators/child.py
octue/twined/cloud/emulators/service.py
octue/twined/cloud/events/__init__.py
octue/twined/cloud/events/answer_question.py
octue/twined/cloud/events/attributes.py
octue/twined/cloud/events/handler.py
octue/twined/cloud/events/question.py
octue/twined/cloud/events/replayer.py
octue/twined/cloud/events/validation.py
octue/twined/cloud/pub_sub/__init__.py
octue/twined/cloud/pub_sub/bigquery.py
octue/twined/cloud/pub_sub/events.py
octue/twined/cloud/pub_sub/logging.py
octue/twined/cloud/pub_sub/service.py
octue/twined/cloud/pub_sub/subscription.py
octue/twined/cloud/pub_sub/topic.py
octue/twined/cloud/registry.py
octue/twined/cloud/service_id.py
octue/twined/compatibility.py
octue/twined/configuration.py
octue-0.69.0.dist-info/METADATA
octue-0.69.0.dist-info/WHEEL
octue-0.69.0.dist-info/entry_points.txt
octue-0.69.0.dist-info/licenses/LICENSE
octue-0.69.0.dist-info/RECORD
