Metadata-Version: 2.4
Name: octue
Version: 0.69.0
Summary: A package providing template applications for data services, and a python SDK to the Octue API.
License: MIT
License-File: LICENSE
Keywords: digital,twins,twined,data,services,science,api,apps,ml,python,schema
Author: Marcus Lugg
Author-email: marcus@octue.com
Requires-Python: >=3.10,<4.0
Classifier: Development Status :: 4 - Beta
Classifier: Intended Audience :: Developers
Classifier: License :: OSI Approved :: MIT License
Classifier: Operating System :: OS Independent
Classifier: Programming Language :: Python :: 3
Classifier: Programming Language :: Python :: 3.10
Classifier: Programming Language :: Python :: 3.11
Classifier: Programming Language :: Python :: 3.12
Classifier: Programming Language :: Python :: 3.13
Classifier: Programming Language :: Python :: 3.14
Classifier: Topic :: Software Development :: Libraries :: Python Modules
Provides-Extra: hdf5
Requires-Dist: click (>=7,<9)
Requires-Dist: coolname (>=2,<3)
Requires-Dist: google-auth (>=1.27.0,<3)
Requires-Dist: google-cloud-bigquery (>=3.18.0,<4.0.0)
Requires-Dist: google-cloud-pubsub (>=2.5,<3.0)
Requires-Dist: google-cloud-secret-manager (>=2.20,<3.0)
Requires-Dist: google-cloud-storage (>=1.35.1,<3)
Requires-Dist: google-crc32c (>=1.1,<2.0)
Requires-Dist: grpcio (>=1.71.0,<2.0.0)
Requires-Dist: h5py (>=3.6,<4.0) ; extra == "hdf5"
Requires-Dist: jsonschema (>=4,<5)
Requires-Dist: packaging (>=20.4)
Requires-Dist: pydash (>=8.0.4,<9.0.0)
Requires-Dist: python-dateutil (>=2.8,<3.0)
Requires-Dist: python-dotenv (>=0,<=2)
Requires-Dist: pyyaml (>=6,<7)
Project-URL: Repository, https://www.github.com/octue/octue-sdk-python
